odin/__init__.py
odin/build/lib/models/__init__.py
odin/build/lib/models/certificate_search_response_model.py
odin/build/lib/models/get_certificate_count.py
odin/build/lib/models/get_certificate_hash_details.py
odin/build/lib/models/get_certificates_summary.py
odin/build/lib/models/get_host_count.py
odin/build/lib/models/get_hosts_ip_details_response.py
odin/build/lib/models/get_hosts_summary_response.py
odin/build/lib/models/search_hosts_response_model.py
odin/example.py
odin/exceptions.py
odin/models/__init__.py
odin/models/certificate_search_response_model.py
odin/models/get_certificate_count.py
odin/models/get_certificate_hash_details.py
odin/models/get_certificates_summary.py
odin/models/get_host_count.py
odin/models/get_hosts_ip_details_response.py
odin/models/get_hosts_summary_response.py
odin/models/search_hosts_response_model.py
odin/odin_client.egg-info/PKG-INFO
odin/odin_client.egg-info/SOURCES.txt
odin/odin_client.egg-info/dependency_links.txt
odin/odin_client.egg-info/requires.txt
odin/odin_client.egg-info/top_level.txt
odin/odin_client.py
odin_cyble-0.0.7.dist-info/METADATA
odin_cyble-0.0.7.dist-info/WHEEL
odin_cyble-0.0.7.dist-info/RECORD
